AUTHORS.rst
CHANGELOG.rst
LICENSE
MANIFEST.in
README.rst
setup.py
jmbo_poll.egg-info/PKG-INFO
jmbo_poll.egg-info/SOURCES.txt
jmbo_poll.egg-info/dependency_links.txt
jmbo_poll.egg-info/not-zip-safe
jmbo_poll.egg-info/requires.txt
jmbo_poll.egg-info/top_level.txt
poll/__init__.py
poll/admin.py
poll/forms.py
poll/models.py
poll/urls.py
poll/views.py
poll/widgets.py
poll/locale/af/LC_MESSAGES/django.mo
poll/locale/af/LC_MESSAGES/django.po
poll/locale/fr/LC_MESSAGES/django.mo
poll/locale/fr/LC_MESSAGES/django.po
poll/migrations/0001_initial.py
poll/migrations/0002_auto__add_field_poll_votes_enabled__add_field_poll_anonymous_votes__ad.py
poll/migrations/__init__.py
poll/templates/poll/poll_detail.html
poll/templates/poll/poll_widget.html
poll/templates/poll/inclusion_tags/poll_detail.html
poll/templates/poll/inclusion_tags/poll_widget.html
poll/templatetags/__init__.py
poll/templatetags/__init__.pyc
poll/templatetags/poll_tags.py
poll/templatetags/poll_tags.pyc